AUTHORS.rst
CHANGELOG.rst
CONTRIBUTING.rst
LICENSE
MANIFEST.in
README.rst
meta.py
setup.cfg
setup.py
ics/__init__.py
ics/__meta__.py
ics/alarm.py
ics/component.py
ics/event.py
ics/icalendar.py
ics/parse.py
ics/timeline.py
ics/todo.py
ics/tools.py
ics/utils.py
ics_lancstimtab.egg-info/PKG-INFO
ics_lancstimtab.egg-info/SOURCES.txt
ics_lancstimtab.egg-info/dependency_links.txt
ics_lancstimtab.egg-info/not-zip-safe
ics_lancstimtab.egg-info/requires.txt
ics_lancstimtab.egg-info/top_level.txt
tests/__init__.py
tests/alarm.py
tests/calendar.py
tests/component.py
tests/contentline.py
tests/event.py
tests/fixture.py
tests/parse.py
tests/test.py
tests/timeline.py
tests/todo.py
tests/unfold_lines.py
tests/utils.py
tests/fixtures/README
tests/fixtures/case_meetup.ics
tests/fixtures/encoding.ics
tests/fixtures/groupscheduled.ics
tests/fixtures/multiple.ics
tests/fixtures/recurrence.ics
tests/fixtures/small.ics
tests/fixtures/time.ics
tests/fixtures/timezoned.ics
tests/gehol/BA1.ics
tests/gehol/BA2.ics
tests/gehol/BA3.ics
tests/gehol/MA1.ics
tests/gehol/MA2.ics