Metadata-Version: 1.1
Name: ics-lancstimtab
Version: 0.5.dev0
Summary: Python icalendar (rfc5545) parser
Home-page: http://github.com/nitros12/ics.py
Author: Nikita Marchant
Author-email: nikita.marchant@gmail.com
License: Apache License, Version 2.0
Keywords: ics icalendar calendar event todo rfc5545 parser pythonic
Platform: UNKNOWN
Classifier: Development Status :: 4 - Beta
Classifier: Topic :: Software Development :: Libraries
Classifier: Topic :: Software Development :: Libraries :: Python Modules
Classifier: Intended Audience :: Developers
Classifier: Topic :: Office/Business :: Scheduling
Classifier: License :: OSI Approved :: Apache Software License
Classifier: Programming Language :: Python
Classifier: Programming Language :: Python :: 3
Classifier: Programming Language :: Python :: 3.4
Classifier: Programming Language :: Python :: 3.5
Classifier: Programming Language :: Python :: 3.6
